dynamodb_json/__init__.py
dynamodb_json/json_util.py
tests/__init__.py
dynamodb_json-1.4.2.dist-info/LICENSE
dynamodb_json-1.4.2.dist-info/METADATA
dynamodb_json-1.4.2.dist-info/WHEEL
dynamodb_json-1.4.2.dist-info/top_level.txt
dynamodb_json-1.4.2.dist-info/RECORD
