Metadata-Version: 2.1
Name: dynamodb-json
Version: 1.4.2
Summary: A DynamoDB json util from and to python objects
Home-page: https://github.com/Alonreznik/dynamodb-json
Author: Alon Reznik
Author-email: alonreznik@gmail.com
License: Mozilla
Keywords: python dynamodb amazon json aws
Classifier: Development Status :: 5 - Production/Stable
Classifier: Intended Audience :: Developers
Classifier: Programming Language :: Python
Classifier: Operating System :: OS Independent
Classifier: Programming Language :: Python :: 2.7
Classifier: Programming Language :: Python :: 3.6
Classifier: Programming Language :: Python :: 3.7
Classifier: Programming Language :: Python :: 3.8
Classifier: Programming Language :: Python :: 3.9
Classifier: Programming Language :: Python :: 3.10
Classifier: Programming Language :: Python :: 3.11
Classifier: Programming Language :: Python :: 3.12
License-File: LICENSE
Requires-Dist: simplejson>=3.10.0
Requires-Dist: boto3>=1.4.0
Requires-Dist: six
